jijcloud/__init__.py
jijcloud/client.py
jijcloud/post_api.py
jijcloud/setting.py
jijcloud/config/__init__.py
jijcloud/config/config_command.py
jijcloud/config/handle_config.py
jijcloud/entity/__init__.py
jijcloud/entity/schema.py
jijcloud/response/__init__.py
jijcloud/response/base.py
jijcloud/response/dimodresopnse.py
jijcloud/sampler/__init__.py
jijcloud/sampler/hubo_cpu.py
jijcloud/sampler/jijmodel_post.py
jijcloud/sampler/sa_cpu.py
jijcloud/sampler/sa_gpu.py
jijcloud/sampler/sampler.py
jijcloud/sampler/sqa_cpu.py
tests/__init__.py
tests/mock_jijcloud_api.py
tests/test_config_command.py
tests/test_config_path.py
tests/test_error_handling.py
tests/test_gpusolver.py
tests/test_openjijsolver.py
jijcloud-1.3.1.dist-info/METADATA
jijcloud-1.3.1.dist-info/WHEEL
jijcloud-1.3.1.dist-info/entry_points.txt
jijcloud-1.3.1.dist-info/top_level.txt
jijcloud-1.3.1.dist-info/RECORD
