Metadata-Version: 2.1
Name: jijcloud
Version: 1.3.1
Summary: UNKNOWN
Home-page: UNKNOWN
Author: Jij Inc.
Author-email: info@j-ij.com
License: MIT
Platform: UNKNOWN
Requires-Dist: dimod
Requires-Dist: requests
Requires-Dist: toml
Requires-Dist: zstandard
Requires-Dist: click
Requires-Dist: jijmodeling (>=0.6.7)
Requires-Dist: pydantic
Requires-Dist: jij-cimod (>=1.1.1)
